[
{"url": "https://www.feedthefeet.com/", "depth": 0},
{"url": "https://www.feedthefeet.com/i", "depth": 0},
{"url": "https://www.feedthefeet.com/n", "depth": 0},
{"url": "https://www.feedthefeet.com/d", "depth": 0},
{"url": "https://www.feedthefeet.com/e", "depth": 0},
{"url": "https://www.feedthefeet.com/x", "depth": 0},
{"url": "https://www.feedthefeet.com/", "depth": 0},
{"url": "https://www.feedthefeet.com/p", "depth": 0},
{"url": "https://www.feedthefeet.com/h", "depth": 0},
{"url": "https://www.feedthefeet.com/p", "depth": 0},
{"url": "https://www.feedthefeet.com/", "depth": 1},
{"url": "https://www.feedthefeet.com/i", "depth": 1},
{"url": "https://www.feedthefeet.com/n", "depth": 1},
{"url": "https://www.feedthefeet.com/d", "depth": 1},
{"url": "https://www.feedthefeet.com/e", "depth": 1},
{"url": "https://www.feedthefeet.com/x", "depth": 1},
{"url": "https://www.feedthefeet.com/", "depth": 1},
{"url": "https://www.feedthefeet.com/p", "depth": 1},
{"url": "https://www.feedthefeet.com/h", "depth": 1},
{"url": "https://www.feedthefeet.com/p", "depth": 1},
{"url": "https://www.feedthefeet.com/", "depth": 1},
{"url": "https://www.feedthefeet.com/i", "depth": 1},
{"url": "https://www.feedthefeet.com/n", "depth": 1},
{"url": "https://www.feedthefeet.com/d", "depth": 1},
{"url": "https://www.feedthefeet.com/e", "depth": 1},
{"url": "https://www.feedthefeet.com/x", "depth": 1},
{"url": "https://www.feedthefeet.com/", "depth": 1},
{"url": "https://www.feedthefeet.com/", "depth": 1},
{"url": "https://www.feedthefeet.com/i", "depth": 1},
{"url": "https://www.feedthefeet.com/n", "depth": 1},
{"url": "https://www.feedthefeet.com/d", "depth": 1},
{"url": "https://www.feedthefeet.com/", "depth": 1},
{"url": "https://www.feedthefeet.com/i", "depth": 1},
{"url": "https://www.feedthefeet.com/n", "depth": 1},
{"url": "https://www.feedthefeet.com/d", "depth": 1},
{"url": "https://www.feedthefeet.com/p", "depth": 1},
{"url": "https://www.feedthefeet.com/h", "depth": 1},
{"url": "https://www.feedthefeet.com/p", "depth": 1},
{"url": "https://www.feedthefeet.com/e", "depth": 1},
{"url": "https://www.feedthefeet.com/x", "depth": 1},
{"url": "https://www.feedthefeet.com/", "depth": 1},
{"url": "https://www.feedthefeet.com/p", "depth": 1},
{"url": "https://www.feedthefeet.com/h", "depth": 1},
{"url": "https://www.feedthefeet.com/p", "depth": 1},
{"url": "https://www.feedthefeet.com/e", "depth": 1},
{"url": "https://www.feedthefeet.com/x", "depth": 1},
{"url": "https://www.feedthefeet.com/", "depth": 1},
{"url": "https://www.feedthefeet.com/p", "depth": 1},
{"url": "https://www.feedthefeet.com/h", "depth": 1},
{"url": "https://www.feedthefeet.com/p", "depth": 1},
{"url": "https://www.feedthefeet.com/", "depth": 1},
{"url": "https://www.feedthefeet.com/i", "depth": 1},
{"url": "https://www.feedthefeet.com/n", "depth": 1},
{"url": "https://www.feedthefeet.com/d", "depth": 1},
{"url": "https://www.feedthefeet.com/", "depth": 1},
{"url": "https://www.feedthefeet.com/i", "depth": 1},
{"url": "https://www.feedthefeet.com/n", "depth": 1},
{"url": "https://www.feedthefeet.com/d", "depth": 1},
{"url": "https://www.feedthefeet.com/e", "depth": 1},
{"url": "https://www.feedthefeet.com/", "depth": 1},
{"url": "https://www.feedthefeet.com/i", "depth": 1},
{"url": "https://www.feedthefeet.com/n", "depth": 1},
{"url": "https://www.feedthefeet.com/d", "depth": 1},
{"url": "https://www.feedthefeet.com/", "depth": 1},
{"url": "https://www.feedthefeet.com/i", "depth": 1},
{"url": "https://www.feedthefeet.com/n", "depth": 1},
{"url": "https://www.feedthefeet.com/d", "depth": 1},
{"url": "https://www.feedthefeet.com/e", "depth": 1},
{"url": "https://www.feedthefeet.com/e", "depth": 1},
{"url": "https://www.feedthefeet.com/x", "depth": 1},
{"url": "https://www.feedthefeet.com/", "depth": 1},
{"url": "https://www.feedthefeet.com/p", "depth": 1},
{"url": "https://www.feedthefeet.com/h", "depth": 1},
{"url": "https://www.feedthefeet.com/p", "depth": 1},
{"url": "https://www.feedthefeet.com/x", "depth": 1},
{"url": "https://www.feedthefeet.com/", "depth": 1},
{"url": "https://www.feedthefeet.com/p", "depth": 1},
{"url": "https://www.feedthefeet.com/h", "depth": 1},
{"url": "https://www.feedthefeet.com/p", "depth": 1},
{"url": "https://www.feedthefeet.com/e", "depth": 1},
{"url": "https://www.feedthefeet.com/x", "depth": 1},
{"url": "https://www.feedthefeet.com/", "depth": 1},
{"url": "https://www.feedthefeet.com/p", "depth": 1},
{"url": "https://www.feedthefeet.com/h", "depth": 1},
{"url": "https://www.feedthefeet.com/p", "depth": 1},
{"url": "https://www.feedthefeet.com/x", "depth": 1},
{"url": "https://www.feedthefeet.com/", "depth": 1},
{"url": "https://www.feedthefeet.com/p", "depth": 1},
{"url": "https://www.feedthefeet.com/h", "depth": 1},
{"url": "https://www.feedthefeet.com/p", "depth": 1}
][
{"url": "https://www.feedthefeet.com/index.php", "depth": 0},
{"url": "https://www.feedthefeet.com/goto/login", "depth": 0},
{"url": "https://www.feedthefeet.com/goto/account", "depth": 0},
{"url": "https://www.feedthefeet.com/goto/login", "depth": 0},
{"url": "https://api.whatsapp.com/send?phone=5531920033909&text=Ol%C3%A1!%20Como%20posso%20ajudar%3F", "depth": 0},
{"url": "https://www.feedthefeet.com/goto/logoff", "depth": 0},
{"url": "https://www.feedthefeet.com/goto/cart", "depth": 0},
{"url": "https://www.feedthefeet.com/index.php", "depth": 0},
{"url": "https://www.feedthefeet.com/goto/account", "depth": 0},
{"url": "https://www.feedthefeet.com/goto/cart", "depth": 0},
{"url": "https://www.feedthefeet.com/colabes/", "depth": 0},
{"url": "https://www.feedthefeet.com/colabes/i-hate-flash-x-feed-the-feet/", "depth": 0},
{"url": "https://www.feedthefeet.com/colabes/ong-amigos-de-sao-francisco/", "depth": 0},
{"url": "https://www.feedthefeet.com/colabes/saquinho-de-lixo-sockinho/", "depth": 0},
{"url": "https://www.feedthefeet.com/kits/", "depth": 0},
{"url": "https://www.feedthefeet.com/kits/kits-prontos/", "depth": 0},
{"url": "https://www.feedthefeet.com/kits/ou-monte-seu-kit/", "depth": 0},
{"url": "https://www.feedthefeet.com/todas-as-meias/", "depth": 0},
{"url": "https://www.feedthefeet.com/todas-as-meias/colecoes/", "depth": 0},
{"url": "https://www.feedthefeet.com/acessorios/", "depth": 0},
{"url": "https://www.feedthefeet.com/linha-pride-lgbtqi/", "depth": 0},
{"url": "https://www.feedthefeet.com/todas-as-meias/", "depth": 0},
{"url": "https://www.feedthefeet.com/colabes/saquinho-de-lixo-sockinho/", "depth": 0},
{"url": "https://www.feedthefeet.com/colabes/saquinho-de-lixo-sockinho/", "depth": 0},
{"url": "https://www.feedthefeet.com/colabes/saquinho-de-lixo-sockinho/", "depth": 0},
{"url": "https://www.feedthefeet.com/", "depth": 0},
{"url": "https://api.whatsapp.com/send?phone=5531920033909&text=Ol%C3%A1!%20Como%20posso%20ajudar%3F", "depth": 0},
{"url": "https://api.whatsapp.com/send?phone=5531920033909&text=Ol%C3%A1!%20Como%20posso%20ajudar%3F", "depth": 0},
{"url": "https://api.whatsapp.com/send?phone=5531920033909&text=Ol%C3%A1!%20Como%20posso%20ajudar%3F", "depth": 0},
{"url": "https://www.feedthefeet.com/todas-as-meias/colecoes/the-old-is-cool-out-of-the-school-to/", "depth": 0},
{"url": "https://www.feedthefeet.com/kits/ou-monte-seu-kit/", "depth": 0},
{"url": "https://www.feedthefeet.com/todas-as-meias/colecoes/smiley-pride/", "depth": 0},
{"url": "https://www.feedthefeet.com/todas-as-meias/colecoes/dama-racer-xadrez/", "depth": 0},
{"url": "https://www.feedthefeet.com/meia-acordada-mas-a-que-custo-saquinho-de-lixo-p92", "depth": 0},
{"url": "https://www.feedthefeet.com/meia-acordada-mas-a-que-custo-saquinho-de-lixo-p92", "depth": 0},
{"url": "https://www.feedthefeet.com/meia-acordada-mas-a-que-custo-saquinho-de-lixo-p92", "depth": 0},
{"url": "https://www.feedthefeet.com/meia-saquinho-saquinho-de-lixo-p91", "depth": 0},
{"url": "https://www.feedthefeet.com/meia-saquinho-saquinho-de-lixo-p91", "depth": 0},
{"url": "https://www.feedthefeet.com/meia-saquinho-saquinho-de-lixo-p91", "depth": 0},
{"url": "https://www.feedthefeet.com/kit-de-meias-do-saquinho-de-lixo-sockinho-p98", "depth": 0},
{"url": "https://www.feedthefeet.com/kit-de-meias-do-saquinho-de-lixo-sockinho-p98", "depth": 0},
{"url": "https://www.feedthefeet.com/kit-de-meias-do-saquinho-de-lixo-sockinho-p98", "depth": 0},
{"url": "https://www.feedthefeet.com/meia-amigos-de-sao-francisco-x-feed-the-feet-p73", "depth": 0},
{"url": "https://www.feedthefeet.com/meia-amigos-de-sao-francisco-x-feed-the-feet-p73", "depth": 0},
{"url": "https://www.feedthefeet.com/meia-amigos-de-sao-francisco-x-feed-the-feet-p73", "depth": 0},
{"url": "https://www.feedthefeet.com/kit-the-old-is-cool-out-of-the-school-too-p100", "depth": 0},
{"url": "https://www.feedthefeet.com/kit-the-old-is-cool-out-of-the-school-too-p100", "depth": 0},
{"url": "https://www.feedthefeet.com/kit-the-old-is-cool-out-of-the-school-too-p100", "depth": 0},
{"url": "https://www.feedthefeet.com/meia-old-school-branca-p89", "depth": 0},
{"url": "https://www.feedthefeet.com/meia-old-school-branca-p89", "depth": 0},
{"url": "https://www.feedthefeet.com/meia-old-school-branca-p89", "depth": 0},
{"url": "https://www.feedthefeet.com/meia-smiley-pride-preta-lgbtqi-p86", "depth": 0},
{"url": "https://www.feedthefeet.com/meia-smiley-pride-preta-lgbtqi-p86", "depth": 0},
{"url": "https://www.feedthefeet.com/meia-smiley-pride-preta-lgbtqi-p86", "depth": 0},
{"url": "https://www.feedthefeet.com/meia-windows-saquinho-de-lixo-p93", "depth": 0},
{"url": "https://www.feedthefeet.com/meia-windows-saquinho-de-lixo-p93", "depth": 0},
{"url": "https://www.feedthefeet.com/meia-windows-saquinho-de-lixo-p93", "depth": 0},
{"url": "https://api.whatsapp.com/send?phone=5531920033909&text=Ol%C3%A1!%20Como%20posso%20ajudar%3F", "depth": 0},
{"url": "https://api.whatsapp.com/send?phone=5531920033909&text=Ol%C3%A1!%20Como%20posso%20ajudar%3F", "depth": 0},
{"url": "https://www.feedthefeet.com/pagina.php?info_id=2", "depth": 0},
{"url": "https://www.feedthefeet.com/pride/", "depth": 0},
{"url": "https://www.feedthefeet.com/outlet/", "depth": 0},
{"url": "https://www.feedthefeet.com/pagina.php?info_id=15", "depth": 0},
{"url": "https://api.whatsapp.com/send?phone=5531920033909&text=Ol%C3%A1!%20Como%20posso%20ajudar%3F", "depth": 0},
{"url": "mailto:feedthefeet@gmail.com", "depth": 0},
{"url": "https://www.facebook.com/feedthefeet/", "depth": 0},
{"url": "https://www.instagram.com/feedthefeetsocks/", "depth": 0},
{"url": "https://www.feedthefeet.com/index.php", "depth": 1},
{"url": "https://www.feedthefeet.com/goto/login", "depth": 1},
{"url": "https://www.feedthefeet.com/goto/account", "depth": 1},
{"url": "https://www.feedthefeet.com/goto/login", "depth": 1},
{"url": "https://api.whatsapp.com/send?phone=5531920033909&text=Ol%C3%A1!%20Como%20posso%20ajudar%3F", "depth": 1},
{"url": "https://www.feedthefeet.com/goto/logoff", "depth": 1},
{"url": "https://www.feedthefeet.com/goto/cart", "depth": 1},
{"url": "https://www.feedthefeet.com/index.php", "depth": 1},
{"url": "https://www.feedthefeet.com/goto/account", "depth": 1},
{"url": "https://www.feedthefeet.com/goto/cart", "depth": 1},
{"url": "https://www.feedthefeet.com/colabes/", "depth": 1},
{"url": "https://www.feedthefeet.com/colabes/i-hate-flash-x-feed-the-feet/", "depth": 1},
{"url": "https://www.feedthefeet.com/colabes/ong-amigos-de-sao-francisco/", "depth": 1},
{"url": "https://www.feedthefeet.com/colabes/saquinho-de-lixo-sockinho/", "depth": 1},
{"url": "https://www.feedthefeet.com/kits/", "depth": 1},
{"url": "https://www.feedthefeet.com/kits/kits-prontos/", "depth": 1},
{"url": "https://www.feedthefeet.com/kits/ou-monte-seu-kit/", "depth": 1},
{"url": "https://www.feedthefeet.com/todas-as-meias/", "depth": 1},
{"url": "https://www.feedthefeet.com/todas-as-meias/colecoes/", "depth": 1},
{"url": "https://www.feedthefeet.com/acessorios/", "depth": 1},
{"url": "https://www.feedthefeet.com/linha-pride-lgbtqi/", "depth": 1},
{"url": "https://www.feedthefeet.com/todas-as-meias/", "depth": 1},
{"url": "https://www.feedthefeet.com/colabes/saquinho-de-lixo-sockinho/", "depth": 1},
{"url": "https://www.feedthefeet.com/colabes/saquinho-de-lixo-sockinho/", "depth": 1},
{"url": "https://www.feedthefeet.com/colabes/saquinho-de-lixo-sockinho/", "depth": 1},
{"url": "https://www.feedthefeet.com/index.php", "depth": 1},
{"url": "https://www.feedthefeet.com/index.php", "depth": 1},
{"url": "https://www.feedthefeet.com/goto/login", "depth": 1},
{"url": "https://www.feedthefeet.com/goto/account", "depth": 1},
{"url": "https://www.feedthefeet.com/index.php", "depth": 1},
{"url": "https://www.feedthefeet.com/goto/login", "depth": 1},
{"url": "https://www.feedthefeet.com/goto/account", "depth": 1},
{"url": "https://www.feedthefeet.com/goto/login", "depth": 1},
{"url": "https://www.feedthefeet.com/index.php", "depth": 1},
{"url": "https://www.feedthefeet.com/goto/login", "depth": 1},
{"url": "https://www.feedthefeet.com/goto/account", "depth": 1},
{"url": "https://www.feedthefeet.com/goto/login", "depth": 1},
{"url": "https://api.whatsapp.com/send?phone=5531920033909&text=Ol%C3%A1!%20Como%20posso%20ajudar%3F", "depth": 1},
{"url": "https://api.whatsapp.com/send?phone=5531920033909&text=Ol%C3%A1!%20Como%20posso%20ajudar%3F", "depth": 1},
{"url": "https://api.whatsapp.com/send?phone=5531920033909&text=Ol%C3%A1!%20Como%20posso%20ajudar%3F", "depth": 1},
{"url": "https://www.feedthefeet.com/todas-as-meias/colecoes/the-old-is-cool-out-of-the-school-to/", "depth": 1},
{"url": "https://www.feedthefeet.com/kits/ou-monte-seu-kit/", "depth": 1},
{"url": "https://www.feedthefeet.com/todas-as-meias/colecoes/smiley-pride/", "depth": 1},
{"url": "https://www.feedthefeet.com/goto/login", "depth": 1},
{"url": "https://api.whatsapp.com/send?phone=5531920033909&text=Ol%C3%A1!%20Como%20posso%20ajudar%3F", "depth": 1},
{"url": "https://www.feedthefeet.com/goto/logoff", "depth": 1},
{"url": "https://www.feedthefeet.com/goto/cart", "depth": 1},
{"url": "https://www.feedthefeet.com/index.php", "depth": 1},
{"url": "https://www.feedthefeet.com/goto/account", "depth": 1},
{"url": "https://www.feedthefeet.com/goto/cart", "depth": 1},
{"url": "https://api.whatsapp.com/send?phone=5531920033909&text=Ol%C3%A1!%20Como%20posso%20ajudar%3F", "depth": 1},
{"url": "https://www.feedthefeet.com/goto/logoff", "depth": 1},
{"url": "https://www.feedthefeet.com/goto/cart", "depth": 1},
{"url": "https://www.feedthefeet.com/index.php", "depth": 1},
{"url": "https://www.feedthefeet.com/goto/account", "depth": 1},
{"url": "https://www.feedthefeet.com/goto/cart", "depth": 1},
{"url": "https://www.feedthefeet.com/colabes/", "depth": 1},
{"url": "https://www.feedthefeet.com/index.php", "depth": 1},
{"url": "https://www.feedthefeet.com/goto/login", "depth": 1},
{"url": "https://www.feedthefeet.com/goto/account", "depth": 1},
{"url": "https://www.feedthefeet.com/goto/login", "depth": 1},
{"url": "https://api.whatsapp.com/send?phone=5531920033909&text=Ol%C3%A1!%20Como%20posso%20ajudar%3F", "depth": 1},
{"url": "https://www.feedthefeet.com/goto/logoff", "depth": 1},
{"url": "https://www.feedthefeet.com/goto/cart", "depth": 1},
{"url": "https://www.feedthefeet.com/index.php", "depth": 1},
{"url": "https://www.feedthefeet.com/goto/account", "depth": 1},
{"url": "https://www.feedthefeet.com/goto/cart", "depth": 1},
{"url": "https://www.feedthefeet.com/index.php", "depth": 1},
{"url": "https://www.feedthefeet.com/goto/login", "depth": 1},
{"url": "https://www.feedthefeet.com/todas-as-meias/colecoes/dama-racer-xadrez/", "depth": 1},
{"url": "https://www.feedthefeet.com/meia-acordada-mas-a-que-custo-saquinho-de-lixo-p92", "depth": 1},
{"url": "https://www.feedthefeet.com/meia-acordada-mas-a-que-custo-saquinho-de-lixo-p92", "depth": 1},
{"url": "https://www.feedthefeet.com/meia-acordada-mas-a-que-custo-saquinho-de-lixo-p92", "depth": 1},
{"url": "https://www.feedthefeet.com/meia-saquinho-saquinho-de-lixo-p91", "depth": 1},
{"url": "https://www.feedthefeet.com/meia-saquinho-saquinho-de-lixo-p91", "depth": 1},
{"url": "https://www.feedthefeet.com/meia-saquinho-saquinho-de-lixo-p91", "depth": 1},
{"url": "https://www.feedthefeet.com/colabes/", "depth": 1},
{"url": "https://www.feedthefeet.com/colabes/i-hate-flash-x-feed-the-feet/", "depth": 1},
{"url": "https://www.feedthefeet.com/colabes/ong-amigos-de-sao-francisco/", "depth": 1},
{"url": "https://www.feedthefeet.com/colabes/saquinho-de-lixo-sockinho/", "depth": 1},
{"url": "https://www.feedthefeet.com/kits/", "depth": 1},
{"url": "https://www.feedthefeet.com/kits/kits-prontos/", "depth": 1},
{"url": "https://www.feedthefeet.com/colabes/i-hate-flash-x-feed-the-feet/", "depth": 1},
{"url": "https://www.feedthefeet.com/colabes/ong-amigos-de-sao-francisco/", "depth": 1},
{"url": "https://www.feedthefeet.com/colabes/saquinho-de-lixo-sockinho/", "depth": 1},
{"url": "https://www.feedthefeet.com/kits/", "depth": 1},
{"url": "https://www.feedthefeet.com/kits/kits-prontos/", "depth": 1},
{"url": "https://www.feedthefeet.com/kits/ou-monte-seu-kit/", "depth": 1},
{"url": "https://api.whatsapp.com/send?phone=5531920033909&text=Ol%C3%A1!%20Como%20posso%20ajudar%3F", "depth": 1},
{"url": "https://www.feedthefeet.com/goto/logoff", "depth": 1},
{"url": "https://www.feedthefeet.com/goto/cart", "depth": 1},
{"url": "https://www.feedthefeet.com/index.php", "depth": 1},
{"url": "https://www.feedthefeet.com/goto/account", "depth": 1},
{"url": "https://www.feedthefeet.com/goto/cart", "depth": 1},
{"url": "https://www.feedthefeet.com/index.php", "depth": 1},
{"url": "https://www.feedthefeet.com/goto/login", "depth": 1},
{"url": "https://www.feedthefeet.com/goto/account", "depth": 1},
{"url": "https://www.feedthefeet.com/colabes/", "depth": 1},
{"url": "https://www.feedthefeet.com/colabes/i-hate-flash-x-feed-the-feet/", "depth": 1},
{"url": "https://www.feedthefeet.com/colabes/ong-amigos-de-sao-francisco/", "depth": 1},
{"url": "https://www.feedthefeet.com/colabes/saquinho-de-lixo-sockinho/", "depth": 1},
{"url": "https://www.feedthefeet.com/kits/", "depth": 1},
{"url": "https://www.feedthefeet.com/kits/kits-prontos/", "depth": 1},
{"url": "https://www.feedthefeet.com/goto/account", "depth": 1},
{"url": "https://www.feedthefeet.com/goto/login", "depth": 1},
{"url": "https://api.whatsapp.com/send?phone=5531920033909&text=Ol%C3%A1!%20Como%20posso%20ajudar%3F", "depth": 1},
{"url": "https://www.feedthefeet.com/goto/logoff", "depth": 1},
{"url": "https://www.feedthefeet.com/goto/cart", "depth": 1},
{"url": "https://www.feedthefeet.com/index.php", "depth": 1},
{"url": "https://www.feedthefeet.com/goto/account", "depth": 1},
{"url": "https://www.feedthefeet.com/index.php", "depth": 1},
{"url": "https://www.feedthefeet.com/goto/login", "depth": 1},
{"url": "https://www.feedthefeet.com/goto/account", "depth": 1},
{"url": "https://www.feedthefeet.com/kit-de-meias-do-saquinho-de-lixo-sockinho-p98", "depth": 1},
{"url": "https://www.feedthefeet.com/kit-de-meias-do-saquinho-de-lixo-sockinho-p98", "depth": 1},
{"url": "https://www.feedthefeet.com/kit-de-meias-do-saquinho-de-lixo-sockinho-p98", "depth": 1},
{"url": "https://www.feedthefeet.com/meia-amigos-de-sao-francisco-x-feed-the-feet-p73", "depth": 1},
{"url": "https://www.feedthefeet.com/meia-amigos-de-sao-francisco-x-feed-the-feet-p73", "depth": 1},
{"url": "https://www.feedthefeet.com/meia-amigos-de-sao-francisco-x-feed-the-feet-p73", "depth": 1},
{"url": "https://www.feedthefeet.com/kits/ou-monte-seu-kit/", "depth": 1},
{"url": "https://www.feedthefeet.com/todas-as-meias/", "depth": 1},
{"url": "https://www.feedthefeet.com/todas-as-meias/colecoes/", "depth": 1},
{"url": "https://www.feedthefeet.com/acessorios/", "depth": 1},
{"url": "https://www.feedthefeet.com/linha-pride-lgbtqi/", "depth": 1},
{"url": "https://www.feedthefeet.com/colabes/i-hate-flash-x-feed-the-feet/", "depth": 1},
{"url": "https://www.feedthefeet.com/index.php", "depth": 1},
{"url": "https://www.feedthefeet.com/goto/login", "depth": 1},
{"url": "https://www.feedthefeet.com/todas-as-meias/", "depth": 1},
{"url": "https://www.feedthefeet.com/todas-as-meias/colecoes/", "depth": 1},
{"url": "https://www.feedthefeet.com/acessorios/", "depth": 1},
{"url": "https://www.feedthefeet.com/linha-pride-lgbtqi/", "depth": 1},
{"url": "https://www.feedthefeet.com/meia-i-hate-flash-x-feed-the-feet-lgbtqi+-p72", "depth": 1},
{"url": "https://www.feedthefeet.com/meia-i-hate-flash-x-feed-the-feet-lgbtqi+-p72", "depth": 1},
{"url": "https://www.feedthefeet.com/meia-i-hate-flash-x-feed-the-feet-lgbtqi+-p72", "depth": 1},
{"url": "https://www.feedthefeet.com/colabes/", "depth": 1},
{"url": "https://www.feedthefeet.com/colabes/i-hate-flash-x-feed-the-feet/", "depth": 1},
{"url": "https://www.feedthefeet.com/colabes/ong-amigos-de-sao-francisco/", "depth": 1},
{"url": "https://www.feedthefeet.com/colabes/saquinho-de-lixo-sockinho/", "depth": 1},
{"url": "https://www.feedthefeet.com/kits/", "depth": 1},
{"url": "https://www.feedthefeet.com/kits/kits-prontos/", "depth": 1},
{"url": "https://www.feedthefeet.com/goto/login", "depth": 1},
{"url": "https://api.whatsapp.com/send?phone=5531920033909&text=Ol%C3%A1!%20Como%20posso%20ajudar%3F", "depth": 1},
{"url": "https://www.feedthefeet.com/goto/logoff", "depth": 1},
{"url": "https://www.feedthefeet.com/goto/cart", "depth": 1},
{"url": "https://www.feedthefeet.com/index.php", "depth": 1},
{"url": "https://www.feedthefeet.com/goto/account", "depth": 1},
{"url": "https://www.feedthefeet.com/goto/cart", "depth": 1},
{"url": "https://www.feedthefeet.com/kits/ou-monte-seu-kit/", "depth": 1},
{"url": "https://www.feedthefeet.com/todas-as-meias/", "depth": 1},
{"url": "https://www.feedthefeet.com/todas-as-meias/colecoes/", "depth": 1},
{"url": "https://www.feedthefeet.com/acessorios/", "depth": 1},
{"url": "https://www.feedthefeet.com/linha-pride-lgbtqi/", "depth": 1},
{"url": "https://www.feedthefeet.com/meia-amigos-de-sao-francisco-x-feed-the-feet-p73", "depth": 1},
{"url": "https://www.feedthefeet.com/goto/cart", "depth": 1},
{"url": "https://www.feedthefeet.com/colabes/", "depth": 1},
{"url": "https://www.feedthefeet.com/colabes/i-hate-flash-x-feed-the-feet/", "depth": 1},
{"url": "https://www.feedthefeet.com/colabes/ong-amigos-de-sao-francisco/", "depth": 1},
{"url": "https://www.feedthefeet.com/colabes/saquinho-de-lixo-sockinho/", "depth": 1},
{"url": "https://www.feedthefeet.com/kits/", "depth": 1},
{"url": "https://www.feedthefeet.com/goto/login", "depth": 1},
{"url": "https://api.whatsapp.com/send?phone=5531920033909&text=Ol%C3%A1!%20Como%20posso%20ajudar%3F", "depth": 1},
{"url": "https://www.feedthefeet.com/goto/logoff", "depth": 1},
{"url": "https://www.feedthefeet.com/goto/cart", "depth": 1},
{"url": "https://www.feedthefeet.com/index.php", "depth": 1},
{"url": "https://www.feedthefeet.com/goto/account", "depth": 1},
{"url": "https://www.feedthefeet.com/index.php", "depth": 1},
{"url": "https://www.feedthefeet.com/goto/login", "depth": 1},
{"url": "https://www.feedthefeet.com/goto/account", "depth": 1},
{"url": "https://www.feedthefeet.com/goto/login", "depth": 1},
{"url": "https://www.feedthefeet.com/index.php", "depth": 1},
{"url": "https://www.feedthefeet.com/goto/login", "depth": 1},
{"url": "https://www.feedthefeet.com/kit-the-old-is-cool-out-of-the-school-too-p100", "depth": 1},
{"url": "https://www.feedthefeet.com/kit-the-old-is-cool-out-of-the-school-too-p100", "depth": 1},
{"url": "https://www.feedthefeet.com/kit-the-old-is-cool-out-of-the-school-too-p100", "depth": 1},
{"url": "https://www.feedthefeet.com/meia-old-school-branca-p89", "depth": 1},
{"url": "https://www.feedthefeet.com/meia-old-school-branca-p89", "depth": 1},
{"url": "https://www.feedthefeet.com/meia-old-school-branca-p89", "depth": 1},
{"url": "https://www.feedthefeet.com/colabes/ong-amigos-de-sao-francisco/", "depth": 1},
{"url": "https://www.feedthefeet.com/colabes/saquinho-de-lixo-sockinho/", "depth": 1},
{"url": "https://www.feedthefeet.com/kit-de-meias-do-saquinho-de-lixo-sockinho-p98", "depth": 1},
{"url": "https://www.feedthefeet.com/kit-de-meias-do-saquinho-de-lixo-sockinho-p98", "depth": 1},
{"url": "https://www.feedthefeet.com/kit-de-meias-do-saquinho-de-lixo-sockinho-p98", "depth": 1},
{"url": "https://www.feedthefeet.com/meia-link-na-bio-saquinho-de-lixo-p94", "depth": 1},
{"url": "https://www.feedthefeet.com/goto/account", "depth": 1},
{"url": "https://www.feedthefeet.com/goto/login", "depth": 1},
{"url": "https://api.whatsapp.com/send?phone=5531920033909&text=Ol%C3%A1!%20Como%20posso%20ajudar%3F", "depth": 1},
{"url": "https://www.feedthefeet.com/goto/logoff", "depth": 1},
{"url": "https://www.feedthefeet.com/goto/cart", "depth": 1},
{"url": "https://www.feedthefeet.com/index.php", "depth": 1},
{"url": "https://www.feedthefeet.com/pagina.php?info_id=2", "depth": 1},
{"url": "https://www.feedthefeet.com/pride/", "depth": 1},
{"url": "https://www.feedthefeet.com/outlet/", "depth": 1},
{"url": "https://www.feedthefeet.com/pagina.php?info_id=15", "depth": 1},
{"url": "https://api.whatsapp.com/send?phone=5531920033909&text=Ol%C3%A1!%20Como%20posso%20ajudar%3F", "depth": 1},
{"url": "mailto:feedthefeet@gmail.com", "depth": 1},
{"url": "https://www.facebook.com/feedthefeet/", "depth": 1},
{"url": "https://www.feedthefeet.com/kits/ou-monte-seu-kit/", "depth": 